stl/__about__.py
stl/__init__.py
stl/base.py
stl/main.py
stl/mesh.py
stl/py.typed
stl/stl.py
stl/utils.py
numpy_stl-3.1.2.dist-info/LICENSE
numpy_stl-3.1.2.dist-info/METADATA
numpy_stl-3.1.2.dist-info/WHEEL
numpy_stl-3.1.2.dist-info/entry_points.txt
numpy_stl-3.1.2.dist-info/top_level.txt
numpy_stl-3.1.2.dist-info/RECORD
