Metadata-Version: 2.1
Name: numpy-stl
Version: 3.1.2
Summary: Library to make reading, writing and modifying both binary and ascii STL files easy.
Home-page: https://github.com/WoLpH/numpy-stl/
Author: Rick van Hattem
Author-email: Wolph@Wol.ph
License: BSD
Classifier: Development Status :: 6 - Mature
Classifier: Intended Audience :: Developers
Classifier: License :: OSI Approved :: BSD License
Classifier: Operating System :: OS Independent
Classifier: Natural Language :: English
Classifier: Programming Language :: Python
Classifier: Programming Language :: Python :: 3
Classifier: Programming Language :: Python :: 3.6
Classifier: Programming Language :: Python :: 3.7
Classifier: Programming Language :: Python :: 3.8
Classifier: Programming Language :: Python :: 3.9
Classifier: Programming Language :: Python :: 3.10
Classifier: Topic :: Software Development :: Libraries :: Python Modules
Requires-Python: >3.6.0
License-File: LICENSE
Requires-Dist: numpy
Requires-Dist: python-utils>=3.4.5
